ualfred/Notify.tgz
ualfred/__init__.py
ualfred/background.py
ualfred/notify.py
ualfred/update.py
ualfred/util.py
ualfred/web.py
ualfred/workflow.py
ualfred/workflow3.py
ualfred-2.0.0.dist-info/METADATA
ualfred-2.0.0.dist-info/WHEEL
ualfred-2.0.0.dist-info/licenses/LICENCE
ualfred-2.0.0.dist-info/RECORD
