Metadata-Version: 2.1
Name: ualfred
Version: 2.0.0
Summary: Modern Alfred workflow library for Python3
Project-URL: Documentation, https://github.com/ischaojie/ualfred#readme
Project-URL: Issues, https://github.com/ischaojie/ualfred/issues
Project-URL: Source, https://github.com/ischaojie/ualfred
Author-email: chaojie <hi@chaojie.fun>
License-Expression: MIT
License-File: LICENCE
Keywords: alfred,alfred-workflow,python3
Classifier: Development Status :: 5 - Production/Stable
Classifier: Intended Audience :: Developers
Classifier: License :: OSI Approved :: MIT License
Classifier: Natural Language :: English
Classifier: Operating System :: MacOS :: MacOS X
Classifier: Programming Language :: Python :: 3.7
Classifier: Programming Language :: Python :: 3.8
Classifier: Programming Language :: Python :: 3.9
Classifier: Programming Language :: Python :: 3.10
Classifier: Programming Language :: Python :: 3.11
Classifier: Topic :: Software Development :: Libraries
Classifier: Topic :: Software Development :: Libraries :: Application Frameworks
Requires-Python: >=3.7
